SquonkAuth.py
SquonkJob.py
SquonkJobDefinition.py
SquonkServer.py
squonk.py
utils.py
im_pysquonk-1.0.1.dist-info/LICENSE
im_pysquonk-1.0.1.dist-info/METADATA
im_pysquonk-1.0.1.dist-info/WHEEL
im_pysquonk-1.0.1.dist-info/entry_points.txt
im_pysquonk-1.0.1.dist-info/top_level.txt
im_pysquonk-1.0.1.dist-info/RECORD
