Metadata-Version: 2.1
Name: im-pysquonk
Version: 1.0.1
Summary: Pysquonk rest server API
Home-page: https://github.com/InformaticsMatters/pysquonk
Author: Malcolm Peacock
Author-email: malcolm@popmalc.org.uk
License: UNKNOWN
Platform: UNKNOWN
Classifier: Programming Language :: Python :: 3
Classifier: License :: OSI Approved :: MIT License
Classifier: Operating System :: OS Independent
Requires-Python: >=3.6
Requires-Dist: PyYAML (==5.1.2)
Requires-Dist: requests-toolbelt (==0.9.1)
